versiokuvaus.py
setuptools_versiokuvaus-0.1.dist-info/METADATA
setuptools_versiokuvaus-0.1.dist-info/WHEEL
setuptools_versiokuvaus-0.1.dist-info/entry_points.txt
setuptools_versiokuvaus-0.1.dist-info/historia.json
setuptools_versiokuvaus-0.1.dist-info/top_level.txt
setuptools_versiokuvaus-0.1.dist-info/RECORD
