Metadata-Version: 2.4
Name: setuptools-versiokuvaus
Version: 0.1
Summary: Versiokuvauksen tallennus paketoinnin yhteydessä
Author-email: Antti Hautaniemi <antti.hautaniemi@me.com>
License: Tekijänoikeus 2020– Antti Hautaniemi
Project-URL: Homepage, https://github.com/an7oine/setuptools-versiokuvaus.git
Requires-Python: >=3.8
Requires-Dist: GitPython
Requires-Dist: setuptools
